{" sukhumi ": 55, " kabul ": 2751, " episkopi cantonment ": 0, " tirana ": 455, " algiers ": 1047, " pago pago ": 74, " andorra la vella ": 20, " luanda ": 256, " the valley ": 14594, " st. john's ": 2786, " buenos aires ": 3224, " yerevan ": 902, " oranjestad ": 8, " georgetown ": 5006, " canberra ": 3209, " vienna ": 10491, " baku ": 1358, " nassau ": 2821, " manama ": 139, " dhaka ": 1727, " bridgetown ": 177, " minsk ": 1597, " brussels ": 9403, " belmopan ": 32, " porto-novo ": 7, " hamilton ": 24891, " thimphu ": 69, " sucre ": 541, " la paz ": 1046, " sarajevo ": 1173, " gaborone ": 105, " bras\u00edlia ": 643, " road town ": 15, " bandar seri begawan ": 23, " sofia ": 3851, " ouagadougou ": 173, " bujumbura ": 66, " phnom penh ": 622, " yaound\u00e9 ": 179, " ottawa ": 10399, " praia ": 970, " george town ": 138, " bangui ": 131, " n'djamena ": 47, " santiago ": 6420, " beijing ": 19843, " flying fish cove ": 4, " west island ": 78, " bogot\u00e1 ": 519, " moroni ": 313, " avarua ": 5, " san jos\u00e9 ": 558, " zagreb ": 1682, " havana ": 2857, " willemstad ": 28, " nicosia ": 443, " prague ": 5161, " yamoussoukro ": 19, " kinshasa ": 392, " copenhagen ": 4855, " djibouti ": 698, " roseau ": 92, " santo domingo ": 478, " dili ": 522, " hanga roa ": 12, " quito ": 650, " cairo ": 6369, " san salvador ": 317, " malabo ": 61, " asmara ": 123, " tallinn ": 661, " addis ababa ": 890, " stanley ": 23117, " t\u00f3rshavn ": 64, " palikir ": 3, " suva ": 156, " helsinki ": 6880, " paris ": 57874, " cayenne ": 2358, " papeete ": 65, " libreville ": 110, " banjul ": 69, " tbilisi ": 865, " berlin ": 26169, " accra ": 666, " gibraltar ": 2640, " athens ": 10054, " nuuk ": 69, " st. george's ": 687, " hag\u00e5t\u00f1a ": 4, " guatemala city ": 200, " st. peter port ": 6, " conakry ": 103, " bissau ": 54, " port-au-prince ": 544, " tegucigalpa ": 146, " budapest ": 3060, " reykjav\u00edk ": 507, " new delhi ": 3558, " jakarta ": 2375, " tehran ": 6590, " baghdad ": 5047, " dublin ": 14165, " douglas ": 27060, " jerusalem ": 19602, " rome ": 27724, " kingston ": 4683, " tokyo ": 16389, " st. helier ": 13, " amman ": 838, " astana ": 853, " nairobi ": 1895, " tarawa ": 246, " pristina ": 237, " kuwait city ": 61, " bishkek ": 179, " vientiane ": 393, " riga ": 1219, " beirut ": 2240, " maseru ": 33, " monrovia ": 353, " tripoli ": 1654, " vaduz ": 46, " vilnius ": 939, " luxembourg ": 3596, " skopje ": 430, " antananarivo ": 100, " lilongwe ": 99, " kuala lumpur ": 1677, " mal\u00e9 ": 288, " bamako ": 280, " valletta ": 271, " majuro ": 56, " nouakchott ": 74, " port louis ": 48, " mexico city ": 3013, " chisinau ": 99, " monaco ": 2902, " ulaanbaatar ": 110, " podgorica ": 131, " plymouth ": 5497, " rabat ": 377, " maputo ": 282, " naypyidaw ": 28, " stepanakert ": 52, " windhoek ": 134, " yaren ": 9, " kathmandu ": 1411, " amsterdam ": 8693, " noum\u00e9a ": 59, " wellington ": 6096, " managua ": 203, " niamey ": 66, " abuja ": 577, " alofi ": 9, " pyongyang ": 3008, " belfast ": 4624, " saipan ": 458, " oslo ": 4141, " muscat ": 750, " islamabad ": 2025, " ngerulmud ": 6, " panama city ": 526, " port moresby ": 223, " asunci\u00f3n ": 211, " lima ": 4311, " manila ": 5616, " adamstown ": 27, " warsaw ": 5469, " lisbon ": 3962, " san juan ": 4167, " doha ": 1489, " taipei ": 3023, " brazzaville ": 117, " bucharest ": 1155, " moscow ": 24104, " kigali ": 711, " gustavia ": 31, " jamestown ": 975, " basseterre ": 20, " castries ": 62, " marigot ": 39, " st. pierre ": 317, " kingstown ": 177, " apia ": 184, " san marino ": 574, " riyadh ": 1946, " edinburgh ": 10906, " dakar ": 783, " belgrade ": 2504, " victoria ": 25860, " freetown ": 361, " singapore ": 20558, " philipsburg ": 34, " bratislava ": 571, " ljubljana ": 967, " honiara ": 87, " mogadishu ": 572, " hargeisa ": 69, " pretoria ": 1023, " grytviken ": 9, " seoul ": 5507, " tskhinvali ": 44, " juba ": 1044, " madrid ": 13549, " sri jayawardenapura kotte ": 1, " khartoum ": 979, " paramaribo ": 59, " mbabane ": 23, " stockholm ": 5914, " bern ": 1782, " damascus ": 4934, " s\u00e3o tom\u00e9 ": 449, " dushanbe ": 141, " dodoma ": 79, " bangkok ": 3614, " lom\u00e9 ": 197, " nuku\u02bbalofa ": 1, " tiraspol ": 60, " port of spain ": 94, " edinburgh of the seven seas ": 0, " tunis ": 965, " ankara ": 3272, " ashgabat ": 71, " cockburn town ": 7, " funafuti ": 54, " kampala ": 631, " kyiv ": 1187, " abu dhabi ": 2113, " london ": 125681, " washington, d.c. ": 6379, " charlotte amalie ": 17, " montevideo ": 581, " tashkent ": 381, " port vila ": 25, " vatican city ": 458, " caracas ": 1321, " hanoi ": 2035, " cardiff ": 4670, " mata-utu ": 2, " el aai\u00fan ": 2, " sana\u00e1 ": 0, " lusaka ": 348, " harare ": 618, " abkhazia ": 410, " afghanistan ": 22042, " akrotiri and dhekelia ": 5, " albania ": 2365, " algeria ": 2619, " american samoa ": 382, " andorra ": 576, " angola ": 2081, " anguilla ": 303, " antigua and barbuda ": 179, " argentina ": 11128, " armenia ": 3285, " aruba ": 532, " ascension island ": 66, " australia ": 65256, " austria ": 9817, " azerbaijan ": 3903, " bahamas ": 2508, " bahrain ": 2638, " bangladesh ": 8939, " barbados ": 1381, " belarus ": 2477, " belgium ": 9865, " belize ": 1466, " benin ": 1087, " bermuda ": 2764, " bhutan ": 1353, " bolivia ": 2429, " bosnia and herzegovina ": 867, " botswana ": 1561, " brazil ": 21968, " british virgin islands ": 343, " brunei ": 1381, " bulgaria ": 4186, " burkina faso ": 1109, " burundi ": 776, " cambodia ": 3761, " cameroon ": 2758, " canada ": 82578, " cape verde ": 679, " cayman islands ": 807, " central african republic ": 593, " chad ": 7901, " chile ": 9773, " china ": 145733, " christmas island ": 326, " cocos islands ": 23, " cocos (keeling) islands ": 0, " colombia ": 6627, " comoros ": 267, " cook islands ": 402, " costa rica ": 3480, " croatia ": 4978, " cuba ": 11724, " cura\u00e7ao ": 298, " cyprus ": 5221, " czech republic ": 3583, " c\u00f4te d'ivoire ": 445, " democratic republic of the congo ": 703, " denmark ": 9862, " dominica ": 576, " dominican republic ": 1872, " east timor ": 528, " timor-leste ": 285, " east timor (timor-leste) ": 0, " easter island ": 434, " ecuador ": 3613, " egypt ": 22735, " el salvador ": 2226, " equatorial guinea ": 399, " eritrea ": 1094, " estonia ": 2711, " ethiopia ": 5835, " falkland islands ": 485, " faroe islands ": 413, " federated states of micronesia ": 90, " fiji ": 3699, " finland ": 8733, " france ": 73724, " french guiana ": 392, " french polynesia ": 324, " gabon ": 727, " gambia ": 1162, " georgia ": 38179, " germany ": 65068, " ghana ": 5701, " greece ": 18622, " greenland ": 4092, " grenada ": 808, " guam ": 2262, " guatemala ": 3361, " guernsey ": 1303, " guinea ": 12949, " guinea-bissau ": 226, " guyana ": 1147, " haiti ": 5676, " honduras ": 3147, " hungary ": 7335, " iceland ": 5389, " india ": 102282, " indonesia ": 10959, " iran ": 43987, " iraq ": 41592, " ireland ": 37934, " isle of man ": 858, " israel ": 75904, " italy ": 36082, " jamaica ": 5357, " japan ": 64727, " jersey ": 45007, " jordan ": 33613, " kazakhstan ": 3008, " kenya ": 9592, " kiribati ": 491, " kosovo ": 4349, " kuwait ": 3212, " kyrgyzstan ": 882, " laos ": 2644, " latvia ": 1857, " lebanon ": 7913, " lesotho ": 654, " liberia ": 2122, " libya ": 7271, " liechtenstein ": 661, " lithuania ": 2775, " macedonia ": 3506, " madagascar ": 2188, " malawi ": 2353, " malaysia ": 11514, " maldives ": 1417, " mali ": 3844, " malta ": 3878, " marshall islands ": 384, " mauritania ": 802, " mauritius ": 1216, " mexico ": 49106, " moldova ": 1395, " mongolia ": 2120, " montenegro ": 1866, " montserrat ": 485, " morocco ": 4578, " mozambique ": 1764, " myanmar ": 4603, " nagorno-karabakh republic ": 13, " namibia ": 1389, " nauru ": 651, " nepal ": 6487, " netherlands ": 17347, " new caledonia ": 522, " new zealand ": 33811, " nicaragua ": 2465, " niger ": 3288, " nigeria ": 11060, " niue ": 106, " norfolk island ": 260, " north korea ": 13890, " northern cyprus ": 157, " united kingdom northern ireland ": 0, " northern mariana islands ": 180, " norway ": 12572, " oman ": 2504, " pakistan ": 31249, " palau ": 644, " palestine ": 8661, " panama ": 6849, " papua new guinea ": 1404, " paraguay ": 1748, " peru ": 5686, " philippines ": 12806, " pitcairn islands ": 33, " poland ": 17333, " portugal ": 11041, " puerto rico ": 9298, " qatar ": 5702, " taiwan ": 15150, " republic of china ": 2471, " republic of china (taiwan) ": 0, " republic of the congo ": 249, " romania ": 5809, " russia ": 68330, " rwanda ": 3269, " saint barth\u00e9lemy ": 25, " saint helena ": 112, " saint kitts and nevis ": 122, " saint lucia ": 200, " saint martin ": 165, " saint pierre and miquelon ": 45, " saint vincent and the grenadines ": 78, " samoa ": 1454, " saudi arabia ": 11804, " scotland ": 25906, " senegal ": 2228, " serbia ": 5904, " seychelles ": 924, " sierra leone ": 2371, " sint maarten ": 111, " slovakia ": 1983, " slovenia ": 2754, " solomon islands ": 767, " somalia ": 3456, " somaliland ": 470, " south africa ": 18176, " south georgia and the south sandwich islands ": 24, " south korea ": 9598, " south ossetia ": 317, " south sudan ": 1501, " spain ": 29766, " sri lanka ": 5915, " sudan ": 5218, " suriname ": 505, " swaziland ": 611, " sweden ": 17373, " switzerland ": 11374, " syria ": 30628, " s\u00e3o tom\u00e9 and pr\u00edncipe ": 0, " tajikistan ": 828, " tanzania ": 3908, " thailand ": 10919, " togo ": 943, " tonga ": 1119, " transnistria ": 144, " trinidad and tobago ": 775, " tristan da cunha ": 58, " tunisia ": 3226, " turkey ": 35505, " turkmenistan ": 789, " turks and caicos islands ": 112, " tuvalu ": 279, " uganda ": 6092, " ukraine ": 20033, " united arab emirates ": 2120, " united kingdom ": 16653, " england ": 100382, " united kingdom; england ": 0, " united states ": 437199, " united states virgin islands ": 0, " uruguay ": 3011, " uzbekistan ": 1357, " vanuatu ": 634, " venezuela ": 8376, " vietnam ": 24253, " wales ": 23425, " wallis and futuna ": 47, " western sahara ": 271, " yemen ": 6352, " zambia ": 2142, " zimbabwe ": 5153, " washington, d.c, ": 56, " i\u0307ran ": 27, " mal\u0131 ": 7, " washington, d.c: ": 9, " cocos keeling islands ": 1, " washington, d c, ": 2, " tbi\u0307li\u0307si\u0307 ": 1, " washington, dick ": 2, " washington, dec. ": 24, " washington, d.c? ": 1, " st- john's ": 1, " washington, dec, ": 2, " washington, d.c\u2026 ": 1, " par\u0131s ": 2, " st, george's ": 1, " washington, d.c_ ": 1, " washington, d c. ": 1, " i\u0307raq ": 1}