{" sukhumi ": 92, " kabul ": 3043, " episkopi cantonment ": 0, " tirana ": 677, " algiers ": 936, " pago pago ": 44, " andorra la vella ": 29, " luanda ": 206, " the valley ": 14731, " st. john's ": 2841, " buenos aires ": 3193, " yerevan ": 597, " oranjestad ": 37, " georgetown ": 5112, " canberra ": 3378, " vienna ": 9747, " baku ": 1041, " nassau ": 3131, " manama ": 98, " dhaka ": 1614, " bridgetown ": 133, " minsk ": 1645, " brussels ": 9942, " belmopan ": 70, " porto-novo ": 10, " hamilton ": 25423, " thimphu ": 140, " sucre ": 552, " la paz ": 1259, " sarajevo ": 1062, " gaborone ": 99, " bras\u00edlia ": 375, " road town ": 21, " bandar seri begawan ": 63, " sofia ": 4383, " ouagadougou ": 128, " bujumbura ": 81, " phnom penh ": 1138, " yaound\u00e9 ": 195, " ottawa ": 10565, " praia ": 631, " george town ": 163, " bangui ": 151, " n'djamena ": 70, " santiago ": 6604, " beijing ": 19689, " flying fish cove ": 5, " west island ": 60, " bogot\u00e1 ": 509, " moroni ": 339, " avarua ": 3, " san jos\u00e9 ": 1023, " zagreb ": 1378, " havana ": 2834, " willemstad ": 13, " nicosia ": 369, " prague ": 4711, " yamoussoukro ": 22, " kinshasa ": 443, " copenhagen ": 5195, " djibouti ": 730, " roseau ": 112, " santo domingo ": 676, " dili ": 769, " hanga roa ": 13, " quito ": 855, " cairo ": 6756, " san salvador ": 368, " malabo ": 58, " asmara ": 136, " tallinn ": 675, " addis ababa ": 808, " stanley ": 23479, " t\u00f3rshavn ": 40, " palikir ": 6, " suva ": 237, " helsinki ": 7184, " paris ": 59786, " cayenne ": 3551, " papeete ": 50, " libreville ": 86, " banjul ": 63, " tbilisi ": 857, " berlin ": 28448, " accra ": 557, " gibraltar ": 2369, " athens ": 8656, " nuuk ": 77, " st. george's ": 582, " hag\u00e5t\u00f1a ": 12, " guatemala city ": 305, " st. peter port ": 8, " conakry ": 147, " bissau ": 81, " port-au-prince ": 272, " tegucigalpa ": 116, " budapest ": 3764, " reykjav\u00edk ": 418, " new delhi ": 3850, " jakarta ": 2795, " tehran ": 7161, " baghdad ": 6454, " dublin ": 12726, " douglas ": 27490, " jerusalem ": 19853, " rome ": 27284, " kingston ": 4260, " tokyo ": 17233, " st. helier ": 13, " amman ": 978, " astana ": 951, " nairobi ": 2088, " tarawa ": 183, " pristina ": 327, " kuwait city ": 70, " bishkek ": 210, " vientiane ": 416, " riga ": 1378, " beirut ": 2609, " maseru ": 39, " monrovia ": 330, " tripoli ": 2068, " vaduz ": 77, " vilnius ": 825, " luxembourg ": 3307, " skopje ": 415, " antananarivo ": 57, " lilongwe ": 67, " kuala lumpur ": 1804, " mal\u00e9 ": 355, " bamako ": 205, " valletta ": 245, " majuro ": 108, " nouakchott ": 50, " port louis ": 58, " mexico city ": 3173, " chisinau ": 78, " monaco ": 3123, " ulaanbaatar ": 275, " podgorica ": 135, " plymouth ": 6051, " rabat ": 357, " maputo ": 257, " naypyidaw ": 66, " stepanakert ": 34, " windhoek ": 174, " yaren ": 11, " kathmandu ": 1358, " amsterdam ": 8472, " noum\u00e9a ": 47, " wellington ": 6651, " managua ": 330, " niamey ": 90, " abuja ": 545, " alofi ": 5, " pyongyang ": 2978, " belfast ": 4300, " saipan ": 376, " oslo ": 4266, " muscat ": 859, " islamabad ": 2114, " ngerulmud ": 5, " panama city ": 734, " port moresby ": 276, " asunci\u00f3n ": 340, " lima ": 3953, " manila ": 5434, " adamstown ": 35, " warsaw ": 5414, " lisbon ": 4105, " san juan ": 3976, " doha ": 1581, " taipei ": 2672, " brazzaville ": 166, " bucharest ": 1347, " moscow ": 24126, " kigali ": 352, " gustavia ": 24, " jamestown ": 1165, " basseterre ": 20, " castries ": 40, " marigot ": 43, " st. pierre ": 421, " kingstown ": 175, " apia ": 153, " san marino ": 519, " riyadh ": 2152, " edinburgh ": 10984, " dakar ": 788, " belgrade ": 2612, " victoria ": 27289, " freetown ": 381, " singapore ": 20388, " philipsburg ": 32, " bratislava ": 636, " ljubljana ": 819, " honiara ": 65, " mogadishu ": 606, " hargeisa ": 109, " pretoria ": 922, " grytviken ": 15, " seoul ": 5931, " tskhinvali ": 45, " juba ": 1009, " madrid ": 14190, " sri jayawardenapura kotte ": 0, " khartoum ": 1042, " paramaribo ": 43, " mbabane ": 45, " stockholm ": 5643, " bern ": 1616, " damascus ": 4657, " s\u00e3o tom\u00e9 ": 403, " dushanbe ": 140, " dodoma ": 86, " bangkok ": 3922, " lom\u00e9 ": 159, " nuku\u02bbalofa ": 8, " tiraspol ": 83, " port of spain ": 87, " edinburgh of the seven seas ": 0, " tunis ": 1022, " ankara ": 3167, " ashgabat ": 71, " cockburn town ": 2, " funafuti ": 47, " kampala ": 605, " kyiv ": 1577, " abu dhabi ": 2526, " london ": 127319, " washington, d.c. ": 6287, " charlotte amalie ": 32, " montevideo ": 653, " tashkent ": 419, " port vila ": 47, " vatican city ": 334, " caracas ": 1435, " hanoi ": 2394, " cardiff ": 5216, " mata-utu ": 2, " el aai\u00fan ": 5, " sana\u00e1 ": 0, " lusaka ": 302, " harare ": 579, " abkhazia ": 538, " afghanistan ": 22669, " akrotiri and dhekelia ": 12, " albania ": 2406, " algeria ": 2615, " american samoa ": 494, " andorra ": 566, " angola ": 1939, " anguilla ": 236, " antigua and barbuda ": 208, " argentina ": 10666, " armenia ": 3006, " aruba ": 540, " ascension island ": 122, " australia ": 67031, " austria ": 9059, " azerbaijan ": 3501, " bahamas ": 2238, " bahrain ": 2844, " bangladesh ": 9763, " barbados ": 1505, " belarus ": 2744, " belgium ": 9505, " belize ": 2171, " benin ": 1192, " bermuda ": 2983, " bhutan ": 1745, " bolivia ": 2562, " bosnia and herzegovina ": 950, " botswana ": 1548, " brazil ": 21713, " british virgin islands ": 360, " brunei ": 1518, " bulgaria ": 3862, " burkina faso ": 1148, " burundi ": 858, " cambodia ": 4491, " cameroon ": 2090, " canada ": 84093, " cape verde ": 702, " cayman islands ": 825, " central african republic ": 583, " chad ": 8913, " chile ": 10684, " china ": 150515, " christmas island ": 241, " cocos islands ": 36, " cocos (keeling) islands ": 0, " colombia ": 6643, " comoros ": 318, " cook islands ": 382, " costa rica ": 3667, " croatia ": 4238, " cuba ": 12153, " cura\u00e7ao ": 416, " cyprus ": 4554, " czech republic ": 3455, " c\u00f4te d'ivoire ": 301, " democratic republic of the congo ": 576, " denmark ": 10139, " dominica ": 738, " dominican republic ": 1996, " east timor ": 608, " timor-leste ": 364, " east timor (timor-leste) ": 0, " easter island ": 368, " ecuador ": 3605, " egypt ": 23521, " el salvador ": 2353, " equatorial guinea ": 335, " eritrea ": 1134, " estonia ": 2471, " ethiopia ": 5847, " falkland islands ": 447, " faroe islands ": 401, " federated states of micronesia ": 63, " fiji ": 3495, " finland ": 9024, " france ": 75495, " french guiana ": 365, " french polynesia ": 305, " gabon ": 877, " gambia ": 1111, " georgia ": 38582, " germany ": 64815, " ghana ": 5483, " greece ": 18132, " greenland ": 4224, " grenada ": 711, " guam ": 2011, " guatemala ": 3954, " guernsey ": 981, " guinea ": 12822, " guinea-bissau ": 284, " guyana ": 982, " haiti ": 4408, " honduras ": 2926, " hungary ": 7227, " iceland ": 5125, " india ": 111011, " indonesia ": 10794, " iran ": 47480, " iraq ": 42823, " ireland ": 37413, " isle of man ": 962, " israel ": 77919, " italy ": 34872, " jamaica ": 4947, " japan ": 65878, " jersey ": 44300, " jordan ": 34598, " kazakhstan ": 2688, " kenya ": 9476, " kiribati ": 284, " kosovo ": 4956, " kuwait ": 3817, " kyrgyzstan ": 896, " laos ": 2302, " latvia ": 1760, " lebanon ": 8200, " lesotho ": 686, " liberia ": 2371, " libya ": 8375, " liechtenstein ": 697, " lithuania ": 2395, " macedonia ": 2607, " madagascar ": 2083, " malawi ": 2026, " malaysia ": 11487, " maldives ": 1634, " mali ": 3723, " malta ": 3776, " marshall islands ": 413, " mauritania ": 519, " mauritius ": 1448, " mexico ": 52951, " moldova ": 1417, " mongolia ": 2446, " montenegro ": 1922, " montserrat ": 460, " morocco ": 4310, " mozambique ": 1930, " myanmar ": 4759, " nagorno-karabakh republic ": 19, " namibia ": 1449, " nauru ": 725, " nepal ": 6543, " netherlands ": 17197, " new caledonia ": 539, " new zealand ": 33514, " nicaragua ": 2473, " niger ": 3117, " nigeria ": 10867, " niue ": 140, " norfolk island ": 149, " north korea ": 13759, " northern cyprus ": 182, " united kingdom northern ireland ": 0, " northern mariana islands ": 248, " norway ": 11718, " oman ": 2461, " pakistan ": 32431, " palau ": 661, " palestine ": 9464, " panama ": 7352, " papua new guinea ": 1536, " paraguay ": 1396, " peru ": 5789, " philippines ": 12726, " pitcairn islands ": 37, " poland ": 16828, " portugal ": 10274, " puerto rico ": 8266, " qatar ": 5823, " taiwan ": 14176, " republic of china ": 2569, " republic of china (taiwan) ": 0, " republic of the congo ": 258, " romania ": 5410, " russia ": 71355, " rwanda ": 2999, " saint barth\u00e9lemy ": 19, " saint helena ": 111, " saint kitts and nevis ": 74, " saint lucia ": 185, " saint martin ": 179, " saint pierre and miquelon ": 34, " saint vincent and the grenadines ": 73, " samoa ": 1555, " saudi arabia ": 12466, " scotland ": 26093, " senegal ": 2056, " serbia ": 5233, " seychelles ": 837, " sierra leone ": 2200, " sint maarten ": 105, " slovakia ": 2181, " slovenia ": 2374, " solomon islands ": 700, " somalia ": 3671, " somaliland ": 491, " south africa ": 18477, " south georgia and the south sandwich islands ": 10, " south korea ": 10593, " south ossetia ": 389, " south sudan ": 1610, " spain ": 30014, " sri lanka ": 6613, " sudan ": 5489, " suriname ": 483, " swaziland ": 566, " sweden ": 16926, " switzerland ": 11500, " syria ": 31154, " s\u00e3o tom\u00e9 and pr\u00edncipe ": 0, " tajikistan ": 752, " tanzania ": 4001, " thailand ": 11622, " togo ": 827, " tonga ": 1042, " transnistria ": 207, " trinidad and tobago ": 821, " tristan da cunha ": 57, " tunisia ": 2971, " turkey ": 34614, " turkmenistan ": 598, " turks and caicos islands ": 118, " tuvalu ": 367, " uganda ": 6489, " ukraine ": 22595, " united arab emirates ": 2136, " united kingdom ": 17276, " england ": 99973, " united kingdom; england ": 0, " united states ": 441698, " united states virgin islands ": 0, " uruguay ": 2880, " uzbekistan ": 1480, " vanuatu ": 594, " venezuela ": 8488, " vietnam ": 24220, " wales ": 23989, " wallis and futuna ": 60, " western sahara ": 279, " yemen ": 6727, " zambia ": 2176, " zimbabwe ": 4864, " washington, d.c: ": 23, " st, john's ": 3, " washington, dec. ": 18, " washington, d.c, ": 76, " i\u0307ran ": 35, " cocos keeling islands ": 4, " di\u0307li\u0307 ": 4, " mal\u0131 ": 8, " ni\u0307geri\u0307a ": 1, " washington, d.c; ": 2, " st- pierre ": 2, " washington, d c: ": 1, " washington, d c, ": 1, " washington, dick ": 1, " washington, d.c\" ": 1, " washington, d c. ": 1}