{" sukhumi ": 79, " kabul ": 2847, " episkopi cantonment ": 0, " tirana ": 616, " algiers ": 1107, " pago pago ": 56, " andorra la vella ": 34, " luanda ": 266, " the valley ": 15712, " st. john's ": 2686, " buenos aires ": 3170, " yerevan ": 723, " oranjestad ": 51, " georgetown ": 5390, " canberra ": 3286, " vienna ": 9736, " baku ": 1430, " nassau ": 2630, " manama ": 151, " dhaka ": 1790, " bridgetown ": 136, " minsk ": 1636, " brussels ": 10095, " belmopan ": 25, " porto-novo ": 10, " hamilton ": 26271, " thimphu ": 84, " sucre ": 429, " la paz ": 1318, " sarajevo ": 1373, " gaborone ": 70, " bras\u00edlia ": 408, " road town ": 72, " bandar seri begawan ": 25, " sofia ": 3836, " ouagadougou ": 172, " bujumbura ": 99, " phnom penh ": 1054, " yaound\u00e9 ": 151, " ottawa ": 10392, " praia ": 721, " george town ": 197, " bangui ": 152, " n'djamena ": 42, " santiago ": 6497, " beijing ": 19385, " flying fish cove ": 0, " west island ": 71, " bogot\u00e1 ": 516, " moroni ": 287, " avarua ": 5, " san jos\u00e9 ": 596, " zagreb ": 1654, " havana ": 3073, " willemstad ": 58, " nicosia ": 505, " prague ": 4724, " yamoussoukro ": 18, " kinshasa ": 432, " copenhagen ": 5848, " djibouti ": 606, " roseau ": 105, " santo domingo ": 560, " dili ": 787, " hanga roa ": 7, " quito ": 646, " cairo ": 6577, " san salvador ": 267, " malabo ": 43, " asmara ": 149, " tallinn ": 872, " addis ababa ": 860, " stanley ": 23495, " t\u00f3rshavn ": 53, " palikir ": 2, " suva ": 284, " helsinki ": 6641, " paris ": 59016, " cayenne ": 3009, " papeete ": 53, " libreville ": 79, " banjul ": 52, " tbilisi ": 986, " berlin ": 26173, " accra ": 623, " gibraltar ": 2899, " athens ": 9137, " nuuk ": 75, " st. george's ": 645, " hag\u00e5t\u00f1a ": 5, " guatemala city ": 148, " st. peter port ": 6, " conakry ": 84, " bissau ": 74, " port-au-prince ": 310, " tegucigalpa ": 93, " budapest ": 3363, " reykjav\u00edk ": 496, " new delhi ": 3630, " jakarta ": 2366, " tehran ": 6697, " baghdad ": 5681, " dublin ": 12589, " douglas ": 29390, " jerusalem ": 21618, " rome ": 28412, " kingston ": 4513, " tokyo ": 17301, " st. helier ": 35, " amman ": 981, " astana ": 959, " nairobi ": 2428, " tarawa ": 181, " pristina ": 303, " kuwait city ": 93, " bishkek ": 220, " vientiane ": 293, " riga ": 1460, " beirut ": 2737, " maseru ": 91, " monrovia ": 303, " tripoli ": 2042, " vaduz ": 69, " vilnius ": 874, " luxembourg ": 3230, " skopje ": 435, " antananarivo ": 83, " lilongwe ": 94, " kuala lumpur ": 1795, " mal\u00e9 ": 315, " bamako ": 405, " valletta ": 200, " majuro ": 87, " nouakchott ": 42, " port louis ": 55, " mexico city ": 3381, " chisinau ": 92, " monaco ": 3360, " ulaanbaatar ": 449, " podgorica ": 200, " plymouth ": 5845, " rabat ": 374, " maputo ": 241, " naypyidaw ": 33, " stepanakert ": 36, " windhoek ": 160, " yaren ": 30, " kathmandu ": 1749, " amsterdam ": 9257, " noum\u00e9a ": 71, " wellington ": 6500, " managua ": 280, " niamey ": 95, " abuja ": 604, " alofi ": 10, " pyongyang ": 3017, " belfast ": 4838, " saipan ": 425, " oslo ": 4770, " muscat ": 716, " islamabad ": 1738, " ngerulmud ": 0, " panama city ": 594, " port moresby ": 295, " asunci\u00f3n ": 234, " lima ": 4353, " manila ": 6832, " adamstown ": 12, " warsaw ": 5788, " lisbon ": 4194, " san juan ": 3747, " doha ": 1597, " taipei ": 2551, " brazzaville ": 177, " bucharest ": 1467, " moscow ": 24082, " kigali ": 399, " gustavia ": 93, " jamestown ": 962, " basseterre ": 46, " castries ": 91, " marigot ": 121, " st. pierre ": 318, " kingstown ": 175, " apia ": 178, " san marino ": 547, " riyadh ": 2030, " edinburgh ": 11656, " dakar ": 851, " belgrade ": 2262, " victoria ": 27856, " freetown ": 383, " singapore ": 19439, " philipsburg ": 108, " bratislava ": 772, " ljubljana ": 863, " honiara ": 67, " mogadishu ": 602, " hargeisa ": 44, " pretoria ": 1269, " grytviken ": 14, " seoul ": 6009, " tskhinvali ": 46, " juba ": 837, " madrid ": 13605, " sri jayawardenapura kotte ": 0, " khartoum ": 900, " paramaribo ": 64, " mbabane ": 41, " stockholm ": 6037, " bern ": 2026, " damascus ": 5104, " s\u00e3o tom\u00e9 ": 430, " dushanbe ": 111, " dodoma ": 108, " bangkok ": 4067, " lom\u00e9 ": 138, " nuku\u02bbalofa ": 5, " tiraspol ": 85, " port of spain ": 82, " edinburgh of the seven seas ": 0, " tunis ": 930, " ankara ": 3171, " ashgabat ": 70, " cockburn town ": 13, " funafuti ": 32, " kampala ": 730, " kyiv ": 1284, " abu dhabi ": 2262, " london ": 132016, " washington, d.c. ": 6477, " charlotte amalie ": 114, " montevideo ": 541, " tashkent ": 453, " port vila ": 125, " vatican city ": 303, " caracas ": 1260, " hanoi ": 2297, " cardiff ": 4946, " mata-utu ": 2, " el aai\u00fan ": 3, " sana\u00e1 ": 0, " lusaka ": 342, " harare ": 689, " abkhazia ": 815, " afghanistan ": 21248, " akrotiri and dhekelia ": 8, " albania ": 2504, " algeria ": 2829, " american samoa ": 342, " andorra ": 519, " angola ": 2409, " anguilla ": 341, " antigua and barbuda ": 272, " argentina ": 10807, " armenia ": 3344, " aruba ": 679, " ascension island ": 70, " australia ": 66528, " austria ": 9605, " azerbaijan ": 3499, " bahamas ": 2202, " bahrain ": 3042, " bangladesh ": 9697, " barbados ": 1509, " belarus ": 2623, " belgium ": 9705, " belize ": 1391, " benin ": 1155, " bermuda ": 2594, " bhutan ": 1134, " bolivia ": 2361, " bosnia and herzegovina ": 1032, " botswana ": 1656, " brazil ": 20317, " british virgin islands ": 328, " brunei ": 1302, " bulgaria ": 3986, " burkina faso ": 1016, " burundi ": 835, " cambodia ": 4256, " cameroon ": 2522, " canada ": 82154, " cape verde ": 578, " cayman islands ": 694, " central african republic ": 540, " chad ": 7977, " chile ": 12850, " china ": 149159, " christmas island ": 251, " cocos islands ": 34, " cocos (keeling) islands ": 0, " colombia ": 7167, " comoros ": 400, " cook islands ": 367, " costa rica ": 2836, " croatia ": 3922, " cuba ": 12658, " cura\u00e7ao ": 442, " cyprus ": 4852, " czech republic ": 3290, " c\u00f4te d'ivoire ": 319, " democratic republic of the congo ": 588, " denmark ": 10095, " dominica ": 534, " dominican republic ": 1816, " east timor ": 603, " timor-leste ": 282, " east timor (timor-leste) ": 0, " easter island ": 371, " ecuador ": 3561, " egypt ": 24015, " el salvador ": 1962, " equatorial guinea ": 341, " eritrea ": 1287, " estonia ": 2677, " ethiopia ": 6242, " falkland islands ": 410, " faroe islands ": 322, " federated states of micronesia ": 61, " fiji ": 3856, " finland ": 9183, " france ": 76421, " french guiana ": 382, " french polynesia ": 297, " gabon ": 738, " gambia ": 1067, " georgia ": 39602, " germany ": 61260, " ghana ": 5332, " greece ": 17719, " greenland ": 3747, " grenada ": 730, " guam ": 1983, " guatemala ": 3541, " guernsey ": 1111, " guinea ": 12867, " guinea-bissau ": 320, " guyana ": 1119, " haiti ": 4903, " honduras ": 2618, " hungary ": 7164, " iceland ": 5488, " india ": 107745, " indonesia ": 10230, " iran ": 46630, " iraq ": 41571, " ireland ": 37284, " isle of man ": 1048, " israel ": 82915, " italy ": 33678, " jamaica ": 5058, " japan ": 64766, " jersey ": 45479, " jordan ": 33489, " kazakhstan ": 2825, " kenya ": 9115, " kiribati ": 383, " kosovo ": 4841, " kuwait ": 3592, " kyrgyzstan ": 967, " laos ": 2161, " latvia ": 2033, " lebanon ": 8713, " lesotho ": 685, " liberia ": 1956, " libya ": 7536, " liechtenstein ": 703, " lithuania ": 2797, " macedonia ": 2550, " madagascar ": 2274, " malawi ": 2327, " malaysia ": 11730, " maldives ": 1151, " mali ": 3650, " malta ": 4012, " marshall islands ": 319, " mauritania ": 763, " mauritius ": 1432, " mexico ": 47990, " moldova ": 1200, " mongolia ": 2633, " montenegro ": 2098, " montserrat ": 453, " morocco ": 4448, " mozambique ": 1907, " myanmar ": 5124, " nagorno-karabakh republic ": 21, " namibia ": 1294, " nauru ": 666, " nepal ": 6577, " netherlands ": 18002, " new caledonia ": 638, " new zealand ": 35260, " nicaragua ": 2281, " niger ": 3287, " nigeria ": 11189, " niue ": 162, " norfolk island ": 197, " north korea ": 13692, " northern cyprus ": 149, " united kingdom northern ireland ": 0, " northern mariana islands ": 166, " norway ": 12672, " oman ": 2459, " pakistan ": 30604, " palau ": 723, " palestine ": 11575, " panama ": 6255, " papua new guinea ": 1476, " paraguay ": 1579, " peru ": 6016, " philippines ": 14387, " pitcairn islands ": 34, " poland ": 15721, " portugal ": 10529, " puerto rico ": 9128, " qatar ": 5996, " taiwan ": 14311, " republic of china ": 2491, " republic of china (taiwan) ": 0, " republic of the congo ": 255, " romania ": 5507, " russia ": 67677, " rwanda ": 2765, " saint barth\u00e9lemy ": 13, " saint helena ": 93, " saint kitts and nevis ": 62, " saint lucia ": 135, " saint martin ": 166, " saint pierre and miquelon ": 22, " saint vincent and the grenadines ": 51, " samoa ": 1437, " saudi arabia ": 12779, " scotland ": 27551, " senegal ": 2141, " serbia ": 5877, " seychelles ": 890, " sierra leone ": 2336, " sint maarten ": 74, " slovakia ": 2077, " slovenia ": 2404, " solomon islands ": 711, " somalia ": 3478, " somaliland ": 409, " south africa ": 18666, " south georgia and the south sandwich islands ": 14, " south korea ": 10283, " south ossetia ": 405, " south sudan ": 1490, " spain ": 29495, " sri lanka ": 6314, " sudan ": 5545, " suriname ": 521, " swaziland ": 674, " sweden ": 17191, " switzerland ": 11248, " syria ": 31030, " s\u00e3o tom\u00e9 and pr\u00edncipe ": 0, " tajikistan ": 919, " tanzania ": 4021, " thailand ": 12021, " togo ": 939, " tonga ": 1123, " transnistria ": 232, " trinidad and tobago ": 792, " tristan da cunha ": 86, " tunisia ": 2996, " turkey ": 34222, " turkmenistan ": 743, " turks and caicos islands ": 104, " tuvalu ": 232, " uganda ": 6177, " ukraine ": 19565, " united arab emirates ": 2101, " united kingdom ": 17063, " england ": 101135, " united kingdom; england ": 0, " united states ": 440156, " united states virgin islands ": 0, " uruguay ": 2532, " uzbekistan ": 1435, " vanuatu ": 763, " venezuela ": 8379, " vietnam ": 26050, " wales ": 23920, " wallis and futuna ": 49, " western sahara ": 329, " yemen ": 6618, " zambia ": 2244, " zimbabwe ": 5327, " washington, d.c: ": 21, " washington, d.c; ": 5, " washington, d.c, ": 56, " i\u0307ran ": 20, " mal\u0131 ": 3, " washington, dec. ": 6, " i\u017frael ": 1, " st  george's ": 1, " st- pierre ": 1, " washington, d.c\u201d ": 1, " washington, dick ": 2, " ben\u0131n ": 1, " washington, d,c. ": 1, " washington, d.c? ": 1}