{"sukhumi": 36, "kabul": 2133, "episkopi cantonment": 1, "tirana": 416, "algiers": 896, "pago pago": 81, "andorra la vella": 37, "luanda": 243, "the valley": 8447, "st. john's": 1812, "buenos aires": 3772, "yerevan": 625, "oranjestad": 36, "georgetown": 4203, "canberra": 3156, "vienna": 9175, "baku": 1034, "nassau": 2040, "manama": 233, "dhaka": 1333, "bridgetown": 153, "minsk": 1200, "brussels": 8940, "belmopan": 44, "porto-novo": 36, "hamilton": 17908, "thimphu": 93, "sucre": 352, "la paz": 965, "sarajevo": 981, "gaborone": 164, "bras\u00edlia": 772, "road town": 34, "bandar seri begawan": 55, "sofia": 2916, "ouagadougou": 203, "bujumbura": 99, "phnom penh": 527, "yaound\u00e9": 172, "ottawa": 8874, "praia": 341, "george town": 147, "bangui": 156, "n'djamena": 61, "santiago": 5323, "beijing": 16391, "flying fish cove": 7, "west island": 70, "bogot\u00e1": 611, "moroni": 298, "avarua": 12, "san jos\u00e9": 613, "zagreb": 1371, "havana": 2264, "willemstad": 57, "nicosia": 477, "prague": 4364, "yamoussoukro": 29, "kinshasa": 517, "copenhagen": 5256, "djibouti": 752, "roseau": 92, "santo domingo": 642, "dili": 240, "hanga roa": 8, "quito": 661, "cairo": 5180, "san salvador": 366, "malabo": 61, "asmara": 141, "tallinn": 764, "addis ababa": 859, "stanley": 14209, "t\u00f3rshavn": 35, "palikir": 9, "suva": 238, "helsinki": 9696, "paris": 40305, "cayenne": 1334, "papeete": 58, "libreville": 131, "banjul": 105, "tbilisi": 781, "berlin": 24747, "accra": 723, "gibraltar": 1966, "athens": 6739, "nuuk": 87, "st. george's": 504, "hag\u00e5t\u00f1a": 13, "guatemala city": 298, "st. peter port": 9, "conakry": 188, "bissau": 652, "port-au-prince": 415, "tegucigalpa": 188, "budapest": 3484, "reykjav\u00edk": 302, "new delhi": 7546, "jakarta": 2271, "tehran": 5325, "baghdad": 4020, "dublin": 8973, "douglas": 18656, "jerusalem": 10621, "rome": 16631, "kingston": 3861, "tokyo": 19704, "st. helier": 24, "amman": 1028, "astana": 560, "nairobi": 2120, "tarawa": 147, "pristina": 243, "kuwait city": 162, "bishkek": 205, "vientiane": 218, "riga": 1098, "beirut": 2527, "maseru": 58, "monrovia": 501, "tripoli": 1406, "vaduz": 98, "vilnius": 809, "luxembourg": 3514, "skopje": 438, "antananarivo": 126, "lilongwe": 117, "kuala lumpur": 2246, "mal\u00e9": 186, "bamako": 314, "valletta": 265, "majuro": 77, "nouakchott": 83, "port louis": 72, "mexico city": 3834, "chisinau": 138, "monaco": 3018, "ulaanbaatar": 151, "podgorica": 188, "plymouth": 3920, "rabat": 483, "maputo": 259, "naypyidaw": 53, "stepanakert": 39, "windhoek": 203, "yaren": 9, "kathmandu": 1031, "amsterdam": 10577, "noum\u00e9a": 56, "wellington": 4438, "managua": 295, "niamey": 134, "abuja": 708, "alofi": 9, "pyongyang": 2180, "belfast": 3325, "saipan": 307, "oslo": 4090, "muscat": 609, "islamabad": 2186, "ngerulmud": 1, "panama city": 649, "port moresby": 254, "asunci\u00f3n": 278, "lima": 3774, "manila": 4233, "adamstown": 19, "warsaw": 4544, "lisbon": 2961, "san juan": 2802, "doha": 1491, "taipei": 2750, "brazzaville": 268, "bucharest": 1488, "moscow": 16657, "kigali": 326, "gustavia": 15, "jamestown": 847, "basseterre": 41, "castries": 74, "marigot": 50, "st. pierre": 323, "kingstown": 169, "apia": 143, "san marino": 701, "riyadh": 2057, "edinburgh": 8625, "dakar": 868, "belgrade": 1975, "victoria": 20232, "freetown": 352, "singapore": 15960, "philipsburg": 73, "bratislava": 794, "ljubljana": 784, "honiara": 55, "mogadishu": 530, "hargeisa": 59, "pretoria": 1141, "grytviken": 15, "seoul": 6657, "tskhinvali": 52, "juba": 423, "madrid": 10920, "sri jayawardenapura kotte": 1, "khartoum": 716, "paramaribo": 77, "mbabane": 43, "stockholm": 6141, "bern": 2089, "damascus": 3601, "s\u00e3o tom\u00e9": 256, "dushanbe": 175, "dodoma": 52, "bangkok": 3474, "lom\u00e9": 116, "nuku\u02bbalofa": 3, "tiraspol": 81, "port of spain": 168, "edinburgh of the seven seas": 0, "tunis": 963, "ankara": 2804, "ashgabat": 93, "cockburn town": 7, "funafuti": 52, "kampala": 706, "kyiv": 980, "abu dhabi": 2053, "london": 86163, "washington, d.c.": 49, "charlotte amalie": 72, "montevideo": 827, "tashkent": 411, "port vila": 53, "vatican city": 682, "caracas": 1557, "hanoi": 1380, "cardiff": 3534, "mata-utu": 2, "el aai\u00fan": 13, "sana\u00e1": 1, "lusaka": 285, "harare": 606, "abkhazia": 299, "afghanistan": 16046, "akrotiri and dhekelia": 11, "albania": 2285, "algeria": 3225, "american samoa": 516, "andorra": 666, "angola": 2194, "anguilla": 427, "antigua and barbuda": 309, "argentina": 12129, "armenia": 2495, "aruba": 664, "ascension island": 91, "australia": 61662, "austria": 13590, "azerbaijan": 2822, "bahamas": 2396, "bahrain": 2579, "bangladesh": 6365, "barbados": 1457, "belarus": 2617, "belgium": 14853, "belize": 1313, "benin": 1144, "bermuda": 2264, "bhutan": 1119, "bolivia": 3131, "bosnia and herzegovina": 1374, "botswana": 1455, "brazil": 24487, "british virgin islands": 475, "brunei": 1192, "bulgaria": 4806, "burkina faso": 1337, "burundi": 938, "cambodia": 3324, "cameroon": 2393, "canada": 73176, "cape verde": 658, "cayman islands": 817, "central african republic": 809, "chad": 6119, "chile": 9295, "china": 84917, "christmas island": 254, "cocos islands": 31, "cocos (keeling) islands": 0, "colombia": 7260, "comoros": 388, "cook islands": 397, "costa rica": 3604, "croatia": 4617, "cuba": 8120, "cura\u00e7ao": 337, "cyprus": 3619, "czech republic": 6010, "c\u00f4te d'ivoire": 319, "democratic republic of the congo": 1131, "denmark": 13654, "dominica": 639, "dominican republic": 2476, "east timor": 489, "timor-leste": 241, "east timor (timor-leste)": 0, "easter island": 304, "ecuador": 3834, "egypt": 16354, "el salvador": 2532, "equatorial guinea": 488, "eritrea": 1057, "estonia": 3358, "ethiopia": 4607, "falkland islands": 521, "faroe islands": 450, "federated states of micronesia": 152, "fiji": 2641, "finland": 10712, "france": 67172, "french guiana": 601, "french polynesia": 418, "gabon": 974, "gambia": 992, "georgia": 26855, "germany": 75115, "ghana": 4096, "greece": 14802, "greenland": 2459, "grenada": 890, "guam": 1774, "guatemala": 3600, "guernsey": 794, "guinea": 8567, "guinea-bissau": 0, "guyana": 1289, "haiti": 3561, "honduras": 2879, "hungary": 8678, "iceland": 4906, "india": 65559, "indonesia": 10502, "iran": 25836, "iraq": 22997, "ireland": 27258, "isle of man": 1011, "israel": 31274, "italy": 40051, "jamaica": 4490, "japan": 62902, "jersey": 32515, "jordan": 22257, "kazakhstan": 2945, "kenya": 7408, "kiribati": 425, "kosovo": 2066, "kuwait": 3436, "kyrgyzstan": 1070, "laos": 1869, "latvia": 2542, "lebanon": 6934, "lesotho": 663, "liberia": 1860, "libya": 6287, "liechtenstein": 938, "lithuania": 3301, "macedonia": 2296, "madagascar": 2425, "malawi": 1720, "malaysia": 10185, "maldives": 1039, "mali": 2966, "malta": 3323, "marshall islands": 541, "mauritania": 836, "mauritius": 1292, "mexico": 39126, "moldova": 1427, "mongolia": 2321, "montenegro": 1912, "montserrat": 639, "morocco": 5006, "mozambique": 2000, "myanmar": 3131, "nagorno-karabakh republic": 26, "namibia": 1633, "nauru": 612, "nepal": 4529, "netherlands": 22863, "new caledonia": 678, "new zealand": 23631, "nicaragua": 2474, "niger": 2575, "nigeria": 8790, "niue": 266, "norfolk island": 230, "north korea": 7927, "northern cyprus": 154, "united kingdom northern ireland": 0, "northern mariana islands": 263, "norway": 13716, "oman": 2357, "pakistan": 16538, "palau": 716, "palestine": 6038, "panama": 5108, "papua new guinea": 1881, "paraguay": 1875, "peru": 6642, "philippines": 11507, "pitcairn islands": 80, "poland": 18099, "portugal": 11338, "puerto rico": 6376, "qatar": 4635, "taiwan": 11541, "republic of china": 3246, "republic of china (taiwan)": 0, "republic of the congo": 272, "romania": 6729, "russia": 46094, "rwanda": 2260, "saint barth\u00e9lemy": 44, "saint helena": 187, "saint kitts and nevis": 164, "saint lucia": 292, "saint martin": 269, "saint pierre and miquelon": 66, "saint vincent and the grenadines": 183, "samoa": 1308, "saudi arabia": 11043, "scotland": 19320, "senegal": 2297, "serbia": 4480, "seychelles": 856, "sierra leone": 1907, "sint maarten": 135, "slovakia": 3297, "slovenia": 3303, "solomon islands": 791, "somalia": 3441, "somaliland": 271, "south africa": 18338, "south georgia and the south sandwich islands": 55, "south korea": 12164, "south ossetia": 280, "south sudan": 1194, "spain": 32092, "sri lanka": 5104, "sudan": 4316, "suriname": 657, "swaziland": 602, "sweden": 20528, "switzerland": 20668, "syria": 17702, "s\u00e3o tom\u00e9 and pr\u00edncipe": 0, "tajikistan": 972, "tanzania": 3722, "thailand": 11000, "togo": 1171, "tonga": 1048, "transnistria": 168, "trinidad and tobago": 1042, "tristan da cunha": 92, "tunisia": 3431, "turkey": 24727, "turkmenistan": 864, "turks and caicos islands": 187, "tuvalu": 407, "uganda": 4419, "ukraine": 12409, "united arab emirates": 3586, "united kingdom": 27705, "england": 68217, "united kingdom; england": 0, "united states": 218760, "united states virgin islands": 0, "uruguay": 3183, "uzbekistan": 1635, "vanuatu": 734, "venezuela": 7274, "vietnam": 15159, "wales": 19013, "wallis and futuna": 97, "western sahara": 315, "yemen": 5067, "zambia": 2017, "zimbabwe": 3586, "mal\u0131": 5, "i\u0307ran": 15, "washington, dec ": 15, "st, john's": 1, "washington, d.c ": 29, "cocos keeling islands": 3, "washington, d.c-": 5, "st, george's": 1, "washington, d.c_": 2, "i\u017frael": 1, "i\u0307raq": 1, "washington, dec.": 1, "washington, d.c'": 2, "\u0131taly": 1, "washington, d.c\u2019": 1, "washington, doch": 1, "washington, d.c\u2014": 1}