{"sukhumi": 56, "kabul": 2309, "episkopi cantonment": 2, "tirana": 436, "algiers": 974, "pago pago": 76, "andorra la vella": 24, "luanda": 257, "the valley": 8550, "st. john's": 1766, "buenos aires": 3650, "yerevan": 583, "oranjestad": 23, "georgetown": 4235, "canberra": 3055, "vienna": 9476, "baku": 996, "nassau": 2049, "manama": 243, "dhaka": 1350, "bridgetown": 163, "minsk": 1203, "brussels": 8939, "belmopan": 37, "porto-novo": 41, "hamilton": 17931, "thimphu": 102, "sucre": 346, "la paz": 977, "sarajevo": 1047, "gaborone": 130, "bras\u00edlia": 801, "road town": 30, "bandar seri begawan": 61, "sofia": 2899, "ouagadougou": 201, "bujumbura": 96, "phnom penh": 548, "yaound\u00e9": 147, "ottawa": 9045, "praia": 351, "george town": 147, "bangui": 166, "n'djamena": 50, "santiago": 5457, "beijing": 16472, "flying fish cove": 3, "west island": 51, "bogot\u00e1": 665, "moroni": 288, "avarua": 8, "san jos\u00e9": 622, "zagreb": 1391, "havana": 2341, "willemstad": 56, "nicosia": 517, "prague": 4405, "yamoussoukro": 25, "kinshasa": 506, "copenhagen": 5566, "djibouti": 780, "roseau": 97, "santo domingo": 653, "dili": 239, "hanga roa": 8, "quito": 684, "cairo": 5454, "san salvador": 355, "malabo": 73, "asmara": 141, "tallinn": 722, "addis ababa": 906, "stanley": 14598, "t\u00f3rshavn": 40, "palikir": 7, "suva": 272, "helsinki": 9873, "paris": 40766, "cayenne": 1267, "papeete": 76, "libreville": 131, "banjul": 117, "tbilisi": 779, "berlin": 24599, "accra": 711, "gibraltar": 1961, "athens": 6838, "nuuk": 70, "st. george's": 501, "hag\u00e5t\u00f1a": 13, "guatemala city": 281, "st. peter port": 7, "conakry": 156, "bissau": 570, "port-au-prince": 448, "tegucigalpa": 195, "budapest": 3563, "reykjav\u00edk": 278, "new delhi": 7472, "jakarta": 2307, "tehran": 5440, "baghdad": 4000, "dublin": 8883, "douglas": 18522, "jerusalem": 10730, "rome": 16869, "kingston": 3884, "tokyo": 20238, "st. helier": 15, "amman": 1034, "astana": 562, "nairobi": 2096, "tarawa": 135, "pristina": 235, "kuwait city": 164, "bishkek": 207, "vientiane": 228, "riga": 1061, "beirut": 2635, "maseru": 59, "monrovia": 514, "tripoli": 1442, "vaduz": 94, "vilnius": 789, "luxembourg": 3542, "skopje": 379, "antananarivo": 158, "lilongwe": 100, "kuala lumpur": 2255, "mal\u00e9": 155, "bamako": 332, "valletta": 235, "majuro": 89, "nouakchott": 87, "port louis": 73, "mexico city": 3941, "chisinau": 121, "monaco": 3119, "ulaanbaatar": 164, "podgorica": 195, "plymouth": 3979, "rabat": 506, "maputo": 211, "naypyidaw": 55, "stepanakert": 31, "windhoek": 205, "yaren": 10, "kathmandu": 1026, "amsterdam": 10768, "noum\u00e9a": 62, "wellington": 4421, "managua": 252, "niamey": 112, "abuja": 732, "alofi": 10, "pyongyang": 2178, "belfast": 3254, "saipan": 341, "oslo": 4144, "muscat": 677, "islamabad": 2198, "ngerulmud": 4, "panama city": 616, "port moresby": 244, "asunci\u00f3n": 262, "lima": 3775, "manila": 4353, "adamstown": 26, "warsaw": 4595, "lisbon": 3129, "san juan": 2807, "doha": 1499, "taipei": 2857, "brazzaville": 283, "bucharest": 1547, "moscow": 16699, "kigali": 320, "gustavia": 19, "jamestown": 844, "basseterre": 53, "castries": 66, "marigot": 47, "st. pierre": 343, "kingstown": 191, "apia": 186, "san marino": 716, "riyadh": 2010, "edinburgh": 8846, "dakar": 867, "belgrade": 1975, "victoria": 19992, "freetown": 328, "singapore": 16204, "philipsburg": 61, "bratislava": 852, "ljubljana": 791, "honiara": 64, "mogadishu": 530, "hargeisa": 55, "pretoria": 1174, "grytviken": 17, "seoul": 6766, "tskhinvali": 59, "juba": 433, "madrid": 11056, "sri jayawardenapura kotte": 0, "khartoum": 739, "paramaribo": 91, "mbabane": 38, "stockholm": 6162, "bern": 2054, "damascus": 3558, "s\u00e3o tom\u00e9": 260, "dushanbe": 158, "dodoma": 55, "bangkok": 3465, "lom\u00e9": 142, "nuku\u02bbalofa": 5, "tiraspol": 80, "port of spain": 168, "edinburgh of the seven seas": 0, "tunis": 977, "ankara": 2871, "ashgabat": 121, "cockburn town": 8, "funafuti": 46, "kampala": 746, "kyiv": 1041, "abu dhabi": 2018, "london": 86936, "washington, d.c.": 63, "charlotte amalie": 67, "montevideo": 835, "tashkent": 424, "port vila": 59, "vatican city": 673, "caracas": 1537, "hanoi": 1419, "cardiff": 3575, "mata-utu": 4, "el aai\u00fan": 5, "sana\u00e1": 3, "lusaka": 313, "harare": 581, "abkhazia": 315, "afghanistan": 16298, "akrotiri and dhekelia": 14, "albania": 2285, "algeria": 3223, "american samoa": 513, "andorra": 693, "angola": 2170, "anguilla": 459, "antigua and barbuda": 329, "argentina": 12065, "armenia": 2439, "aruba": 662, "ascension island": 85, "australia": 61639, "austria": 13903, "azerbaijan": 2891, "bahamas": 2462, "bahrain": 2571, "bangladesh": 6474, "barbados": 1466, "belarus": 2598, "belgium": 14944, "belize": 1317, "benin": 1179, "bermuda": 2219, "bhutan": 1196, "bolivia": 3185, "bosnia and herzegovina": 1433, "botswana": 1433, "brazil": 24680, "british virgin islands": 489, "brunei": 1265, "bulgaria": 4824, "burkina faso": 1314, "burundi": 1017, "cambodia": 3395, "cameroon": 2262, "canada": 73733, "cape verde": 638, "cayman islands": 810, "central african republic": 854, "chad": 6274, "chile": 9242, "china": 85621, "christmas island": 250, "cocos islands": 44, "cocos (keeling) islands": 0, "colombia": 7281, "comoros": 405, "cook islands": 452, "costa rica": 3648, "croatia": 4529, "cuba": 8116, "cura\u00e7ao": 340, "cyprus": 3929, "czech republic": 6128, "c\u00f4te d'ivoire": 340, "democratic republic of the congo": 1175, "denmark": 14076, "dominica": 719, "dominican republic": 2543, "east timor": 512, "timor-leste": 249, "east timor (timor-leste)": 0, "easter island": 365, "ecuador": 3911, "egypt": 16624, "el salvador": 2492, "equatorial guinea": 522, "eritrea": 1095, "estonia": 3360, "ethiopia": 4659, "falkland islands": 545, "faroe islands": 486, "federated states of micronesia": 145, "fiji": 2607, "finland": 10839, "france": 66862, "french guiana": 640, "french polynesia": 479, "gabon": 1054, "gambia": 1067, "georgia": 26893, "germany": 75348, "ghana": 4165, "greece": 15162, "greenland": 2447, "grenada": 963, "guam": 1799, "guatemala": 3657, "guernsey": 829, "guinea": 8483, "guinea-bissau": 0, "guyana": 1281, "haiti": 3707, "honduras": 2928, "hungary": 8727, "iceland": 4748, "india": 65161, "indonesia": 10563, "iran": 26090, "iraq": 23124, "ireland": 26979, "isle of man": 1043, "israel": 31659, "italy": 40473, "jamaica": 4488, "japan": 63758, "jersey": 32515, "jordan": 22802, "kazakhstan": 2942, "kenya": 7526, "kiribati": 396, "kosovo": 2095, "kuwait": 3325, "kyrgyzstan": 1083, "laos": 1865, "latvia": 2631, "lebanon": 7026, "lesotho": 663, "liberia": 1898, "libya": 6314, "liechtenstein": 944, "lithuania": 3320, "macedonia": 2354, "madagascar": 2508, "malawi": 1716, "malaysia": 10389, "maldives": 1055, "mali": 2996, "malta": 3422, "marshall islands": 564, "mauritania": 813, "mauritius": 1323, "mexico": 39280, "moldova": 1487, "mongolia": 2381, "montenegro": 1935, "montserrat": 647, "morocco": 5013, "mozambique": 2036, "myanmar": 3339, "nagorno-karabakh republic": 25, "namibia": 1623, "nauru": 551, "nepal": 4578, "netherlands": 23073, "new caledonia": 766, "new zealand": 23306, "nicaragua": 2583, "niger": 2675, "nigeria": 8810, "niue": 276, "norfolk island": 251, "north korea": 7851, "northern cyprus": 164, "united kingdom northern ireland": 0, "northern mariana islands": 300, "norway": 14077, "oman": 2407, "pakistan": 16741, "palau": 768, "palestine": 6300, "panama": 5047, "papua new guinea": 1850, "paraguay": 1760, "peru": 6487, "philippines": 11577, "pitcairn islands": 73, "poland": 18139, "portugal": 11439, "puerto rico": 6539, "qatar": 4580, "taiwan": 11599, "republic of china": 3140, "republic of china (taiwan)": 0, "republic of the congo": 282, "romania": 6764, "russia": 46231, "rwanda": 2338, "saint barth\u00e9lemy": 53, "saint helena": 212, "saint kitts and nevis": 192, "saint lucia": 325, "saint martin": 271, "saint pierre and miquelon": 89, "saint vincent and the grenadines": 180, "samoa": 1275, "saudi arabia": 11191, "scotland": 19493, "senegal": 2293, "serbia": 4704, "seychelles": 836, "sierra leone": 1799, "sint maarten": 137, "slovakia": 3179, "slovenia": 3253, "solomon islands": 798, "somalia": 3640, "somaliland": 260, "south africa": 18325, "south georgia and the south sandwich islands": 61, "south korea": 12312, "south ossetia": 284, "south sudan": 1170, "spain": 32250, "sri lanka": 5245, "sudan": 4422, "suriname": 681, "swaziland": 626, "sweden": 20695, "switzerland": 20802, "syria": 17924, "s\u00e3o tom\u00e9 and pr\u00edncipe": 0, "tajikistan": 940, "tanzania": 3770, "thailand": 11201, "togo": 1149, "tonga": 1032, "transnistria": 143, "trinidad and tobago": 960, "tristan da cunha": 108, "tunisia": 3375, "turkey": 24827, "turkmenistan": 864, "turks and caicos islands": 199, "tuvalu": 388, "uganda": 4466, "ukraine": 12448, "united arab emirates": 3498, "united kingdom": 27636, "england": 68165, "united kingdom; england": 0, "united states": 218677, "united states virgin islands": 0, "uruguay": 3065, "uzbekistan": 1660, "vanuatu": 732, "venezuela": 7054, "vietnam": 15292, "wales": 19010, "wallis and futuna": 124, "western sahara": 262, "yemen": 5042, "zambia": 2084, "zimbabwe": 3640, "i\u0307ran": 18, "i\u0307raq": 2, "cocos keeling islands": 7, "washington, dec ": 23, "washington, d.c ": 30, "washington, d c ": 1, "washington, d.c-": 6, "st, john's": 4, "st: pierre": 2, "washington, d.c_": 10, "vi\u0307etnam": 1, "washington, doc ": 1, "spa\u0131n": 1, "st, george's": 1, "i\u0307srael": 1, "mal\u0131": 3, "washington, dhcd": 1, "li\u0307ma": 1, "washington, d.c\u2026": 2, "austral\u0131a": 1}